imgcmprs/__init__.py
imgcmprs/__main__.py
imgcmprs/img_compress.py
imgcmprs-0.1.1.dist-info/METADATA
imgcmprs-0.1.1.dist-info/WHEEL
imgcmprs-0.1.1.dist-info/entry_points.txt
imgcmprs-0.1.1.dist-info/top_level.txt
imgcmprs-0.1.1.dist-info/RECORD
