Metadata-Version: 2.4
Name: imgcmprs
Version: 0.1.1
Summary: Fast, safe CLI to compress JPEG & PNG, lossless/lossy, batch or single images.
Author: Eyad Mohammed
Requires-Python: >=3.7
Requires-Dist: Pillow
Dynamic: author
Dynamic: description
Dynamic: description-content-type
Dynamic: requires-dist
Dynamic: requires-python
Dynamic: summary
